bp_quant/alignment/__init__.py
bp_quant/alignment/generate_alignment.py
bp_quant/general/__init__.py
bp_quant/general/command_line.py
bp_quant/general/pipeline.py
bp_quant/general/version.py
bp_quant/indexing/__init__.py
bp_quant/indexing/generate_index.py
bp_quant/io/__init__.py
bp_quant/io/csv_to_fasta.py
bp_quant/io/file_handler.py
bp_quant/io/file_headers.py
bp_quant/io/io_methods.py
bp_quant/io/seq_table.py
bp_quant/plotting/__init__.py
bp_quant/plotting/plot_reads.py
bp_quant/quantification/__init__.py
bp_quant/quantification/counting.py
bp_quant/quantification/coverage.py
bp_quant/quantification/read_classification.py
bp_quant/quantification/read_processing.py
bp_quant/quantification/requantify.py
bp_quant/validation/__init__.py
bp_quant/validation/alignment_info.py
bp_quant-0.6.0.dist-info/LICENSE
bp_quant-0.6.0.dist-info/METADATA
bp_quant-0.6.0.dist-info/WHEEL
bp_quant-0.6.0.dist-info/entry_points.txt
bp_quant-0.6.0.dist-info/top_level.txt
bp_quant-0.6.0.dist-info/RECORD
