Metadata-Version: 2.1
Name: bp_quant
Version: 0.6.0
Summary: Quantification of reads at defined positions to verify custom input sequences. Given a gene fusion or splicing junction of interest, this tool can quantify RNA-seq reads supporting the breakpoint (or splice junction) by quantifying reads that map to the breakpoint (junction reads) and read pairs that span the breakpoint (spanning pairs).
Author-email: TRON - Translational Oncology at the University Medical Center of the Johannes Gutenberg University Mainz <patrick.sorn@tron-mainz.de>
Maintainer-email: Patrick Sorn <patrick.sorn@tron-mainz.de>, Jonas Ibn-Salem <jonas.ibn-salem@tron-mainz.de>, Franziska Lang <franziska.lang@tron-mainz.de>, Johannes Hausmann <johannes.hausmann@tron-mainz.de>
Project-URL: Homepage, https://github.com/tron-bioinformatics/easyquant
Classifier: Development Status :: 4 - Beta
Classifier: Intended Audience :: Healthcare Industry
Classifier: Intended Audience :: Science/Research
Classifier: Topic :: Scientific/Engineering :: Bio-Informatics
Classifier: Programming Language :: Python :: 3.8
Classifier: Programming Language :: Python :: 3.9
Classifier: Programming Language :: Python :: 3.10
Classifier: Programming Language :: Python :: 3 :: Only
Classifier: License :: OSI Approved :: MIT License
Classifier: Operating System :: Unix
Requires-Python: >=3.8
License-File: LICENSE
Requires-Dist: pysam ==0.21.0
Requires-Dist: matplotlib ==3.5.2
Requires-Dist: biopython ==1.81
